LICENSE
MANIFEST.in
README.md
README.rst
setup.cfg
setup.py
tests/__init__.py
tests/sshserver.py
tests/test_app.py
tests/test_handler.py
tests/test_main.py
tests/test_policy.py
tests/test_settings.py
tests/test_utils.py
tests/utils.py
tests/data/cert.crt
tests/data/cert.key
tests/data/host_keys_test.db
tests/data/known_hosts_example
tests/data/known_hosts_example2
tests/data/known_hosts_example3
tests/data/test_ed25519.key
tests/data/test_ed25519_password.key
tests/data/test_known_hosts
tests/data/test_new_dsa.key
tests/data/test_new_rsa_password.key
tests/data/test_rsa.key
tests/data/test_rsa_password.key
tests/data/user_rsa_key
webssh/__init__.py
webssh/_version.py
webssh/handler.py
webssh/main.py
webssh/policy.py
webssh/settings.py
webssh/utils.py
webssh/worker.py
webssh.egg-info/PKG-INFO
webssh.egg-info/SOURCES.txt
webssh.egg-info/dependency_links.txt
webssh.egg-info/entry_points.txt
webssh.egg-info/requires.txt
webssh.egg-info/top_level.txt
webssh/static/css/bootstrap.min.css
webssh/static/css/fullscreen.min.css
webssh/static/css/xterm.min.css
webssh/static/img/favicon.png
webssh/static/js/bootstrap.min.js
webssh/static/js/jquery.min.js
webssh/static/js/main.js
webssh/static/js/popper.min.js
webssh/static/js/xterm-addon-fit.min.js
webssh/static/js/xterm.min.js
webssh/templates/index.html