Metadata-Version: 1.1
Name: webssh
Version: 1.5.0
Summary: Web based ssh client
Home-page: https://github.com/huashengdun/webssh
Author: Shengdun Hua
Author-email: webmaster0115@gmail.com
License: MIT
Platform: UNKNOWN
Classifier: Programming Language :: Python
Classifier: Programming Language :: Python :: 2
Classifier: Programming Language :: Python :: 2.7
Classifier: Programming Language :: Python :: 3
Classifier: Programming Language :: Python :: 3.4
Classifier: Programming Language :: Python :: 3.5
Classifier: Programming Language :: Python :: 3.6
Classifier: Programming Language :: Python :: 3.7
